Verilog/v1-r1-MMA/Include/controlSignal.v
//================================================================--
// Design Unit	: control names (include)
//
// File Name	: controlSignal.v
//
// Purpose	: include file with control signal names
//
// Author	: Peter Walsh, Vancouver Island University
//
// Environmant	: Icarus
//-------------------------------------------------------------------
// Revision List	
// Version	Author		Date	   Changes
// 1.0		PW		Nov 2016   New version
// 2.0          Sami Al-Qusus   Nov 2018   Modified for MMA 
//================================================================--

//Control signals are all asserted active-high.
//The define macros below are used to enhance readability
//by replacing references like control[0] with control[HALT].
//
//Registers
//---------
//Program counter (PC) 12 bits
//ALU registers (R0, R1, R2, R3) 8 bits each
//Instruction Register (IR) 16 bits
//
//Busses/Signals
//--------------
//Internal address bus (int_abus) 12 bits
//Internal read data bus (int_rbus) 16 bits
//Internal write data bus (int_wbus) 16 bits
//ALU output (alu_out) 8 bits

`define MAX_CONTROL_LINES 14
//control[0:MAX_CONTROL_LINES-1]

`define WE 0 
// (WE) ? MEM mwmoey write cycle : memory read cycle
`define INIT_PC 1
// PC <= 0 
`define INC_PC 2
// PC <=  PC + 1
`define IR_RBUS 3
// IR <= int_rbus 
`define R0_RBUS 4
// R0 <= int_rbus 
`define ACC_RBUS 5
// R1 <= int_rbus 
`define WBUS_ACC 6
// int_wbus <= ACC
`define ACC_ALU 7
// int_wbus <= alu
`define ADD_OP 8
// R0 + R1
`define SUB_OP 9 
// R1 - R0
`define ABUS_MR 10
// int_abus <= MR
`define ABUS_PC 11
// int_abus <= PC
`define PC_R0 12
// PC <= R0
`define MR_R0 13
// MR <=  R0

Verilog/v1-r1-MMA/Include/controlParam.v
// Include file with control unit parameters automatically generated by paramParam`Gen.pl 
// P. Walsh Nov 2016 
// Sami Al-Qusus   Nov 2018   Modified for MMA 
`define INIT0 0
`define INIT1 1
`define INIT2 2
`define INIT3 3
`define LDA0 4
`define LDA1 5
`define LDA2 6
`define LDA3 7
`define LDA4 8
`define STO0 9
`define STO1 10
`define STO2 11
`define ADD0 12
`define ADD1 13
`define ADD2 14
`define ADD3 15
`define ADD4 16
`define ADD5 17
`define ADD6 18
`define SUB0 19
`define SUB1 20
`define SUB2 21
`define SUB3 22
`define SUB4 23
`define SUB5 24
`define SUB6 25
`define JNE0 26
`define JNE1 27
`define JMP0 28
`define JMP1 29

Verilog/v1-r1-MMA/Control_Unit/behaviour.v
//================================================================--
// Design Unit	: Control Unit (behaviour)
//
// File Name	: behaviour.v
//
// Purpose	: implement the MMA Control Unit FSM
//
// Author	: Peter Walsh, Vancouver Island University
//
// Environmant	: Icarus
//-------------------------------------------------------------------
// Revision List	
// Version	Author  	Date	    Changes
// 1.0		PW	        Nov 2016   New version
// 2.0          Sami Al-Qusus   Nov 2018   MMA 
//================================================================--

`include "controlSignal.v"
`include "controlParam.v"

module control_unit (control, clk, opcode, psw, reset, halt, fault, break); 

   input wire clk;
   input wire reset;
   input wire [3:0] opcode;
   input wire [15:0] psw;
   output reg [0:`MAX_CONTROL_LINES-1] control;
   output reg halt, fault, break;

   reg [4:0] state, nextState;

   task clearControl;

      integer i;

      begin
         for (i=0; i<`MAX_CONTROL_LINES; i=i+1)
            control[i] <= 1'b0;
         #1;
      end

   endtask

   // state assignment

   always @(posedge clk, posedge reset) begin
      if (reset == 1'b1) begin
         state <= `INIT0;
         halt <= 1'b0;
         fault <= 1'b0;
         break <= 1'b0;
      end else 
         state <= nextState;
   end

   // next state and output  functions

   always @(state, opcode, psw) begin
      case (state)
         `INIT0: begin
            clearControl();
            control[`INIT_PC] <= 1'b1; 
            nextState <= `INIT1;
         end
         `INIT1: begin
            clearControl();
            control[`ABUS_PC] <= 1'b1; 
            control[`WE] <= 1'b0; 
            break <= 1'b0;
            nextState <= `INIT2;
         end
         `INIT2: begin
            clearControl();
            control[`IR_RBUS] <= 1'b1; 
            control[`INC_PC] <= 1'b1; 
            nextState <= `INIT3;
         end
         `INIT3: begin
            clearControl();
            case (opcode) 
               4'h0 : begin
                  // nop
                  break <= 1'b1;
                  nextState <= `INIT1;
               end
               4'h1 : begin
                  // halt
                  break <= 1'b1;
                  halt <= 1'b1;
               end
               4'h2 : begin
                  nextState <= `LDA0;
               end
               4'h3 : begin
                  nextState <= `STO0;
               end
	       4'h4 : begin
		  nextState <= `ADD0;
	       end
	       4'h5 : begin
		  nextState <= `SUB0;
	       end
	       4'h6 : begin
                   nextState <= `JMP0;
               end
               4'h7 : begin
                  nextState <= `JNE0;
               end
               default : fault <= 1'b1;
            endcase
         end
         `LDA0 : begin
            clearControl();
            control[`R0_RBUS] <= 1'b1; 
          //  control[`MR_R0] <= 1'b1;
            nextState <= `LDA1;
         end
	 `LDA1 : begin
		 clearControl();
		 control[`MR_R0] <= 1'b1;
		 nextState <= `LDA2;
	 end
         `LDA2 : begin
            clearControl();
            control[`ABUS_MR]<= 1'b1;
            control[`WE] <= 1'b0; 
            nextState <= `LDA3;
         end
         `LDA3 : begin
          clearControl();
            control[`ACC_RBUS]<= 1'b1;
            nextState <= `LDA4;
         end
         `LDA4 : begin
          clearControl();
            //control[`INC_PC]<= 1'b1;
            nextState <= `INIT1;
         end
         `STO0 : begin
            clearControl();
            control[`R0_RBUS] <= 1'b1; 
          //  control[`MR_R0] <= 1'b1;
            nextState <= `STO1;
         end
	 `STO1 : begin
		 clearControl();
		 control[`MR_R0] <= 1'b1;
		 nextState <= `STO2;
	 end
         `STO2 : begin
		 clearControl();
            control[`WBUS_ACC] <= 1'b1; 
            control[`ABUS_MR]<= 1'b1;
            control[`WE] <= 1'b1;
            nextState <= `INIT1;
         end
         `ADD0 : begin
            clearControl();
            control[`R0_RBUS] <= 1'b1; 
	    nextState <= `ADD1;
    	  end
	  `ADD1 : begin
            clearControl();
            control[`MR_R0] <= 1'b1;
            nextState <= `ADD2;
         end
         `ADD2 : begin
            clearControl();
            control[`ABUS_MR] <= 1'b1;
            control[`WE] <= 1'b0;
            nextState <= `ADD3;
         end
         `ADD3 : begin
            clearControl();
            control[`R0_RBUS]<= 1'b1;
            nextState <= `ADD4;
         end
         `ADD4 : begin
            clearControl();
            control[`ADD_OP] <= 1'b1;
            nextState <= `ADD5;
         end
         `ADD5 : begin
            clearControl();
            control[`ACC_ALU] <= 1'b1;
            nextState <= `ADD6;
         end
     
         `ADD6 : begin
		 clearControl();
           // control[`INC_PC] <= 1'b1;
            break <= 1'b0;
            nextState <= `INIT1;
         end
         `SUB0 : begin
            clearControl();
            control[`R0_RBUS] <= 1'b1; 
          //  control[`MR_R0] <= 1'b1;
            nextState <= `SUB1;
         end
	 `SUB1 : begin
	   clearControl();
       	   control[`MR_R0] <= 1'b1;
 	   nextState <= `SUB2;
	end 
	`SUB2 : begin
            clearControl();
            control[`ABUS_MR] <= 1'b1;
            control[`WE] <= 1'b0;
	    nextState <= `SUB3;
    end
         `SUB3 : begin
            clearControl();
            control[`R0_RBUS]<= 1'b1;
            nextState <= `SUB4;
         end
         `SUB4 : begin
            clearControl();
            control[`SUB_OP] <= 1'b1;
            nextState <= `SUB5;
         end
         `SUB5 : begin
            clearControl();
            control[`ACC_ALU] <= 1'b1;
            nextState <= `SUB6;
         end
         `SUB6 : begin
		 clearControl();
            //control[`INC_PC] <= 1'b1;
            break <= 1'b0;
            nextState <= `INIT1;
         end
         
	 
         `JMP0 : begin
	     	clearControl();
	     	control[`R0_RBUS]<= 1'b1;
	     	nextState <= `JMP1;
	 end
	 
	 `JMP1 : begin
		 clearControl();
	     control[`PC_R0] <= 1'b1;
	     break <= 1'b0;
	     nextState <= `INIT1;
     	end
	 `JNE0 : begin
		 clearControl();
		 control[`R0_RBUS]<= 1'b1;
		 nextState <= `JNE1;
	 end
         `JNE1 : begin
            clearControl();
            if (psw[15] == 1'b0) begin
               // jump
               clearControl();
               control[`PC_R0] <= 1'b1;
               break <= 1'b0;
               nextState <= `INIT1;
            end else begin
               nextState <= `INIT1;
            end
         end   
      endcase
   end

endmodule

Verilog/v1-r1-MMA/Control_Unit/tb.v
//================================================================--
// Design Unit  : cew testbench for control_unit
//
// File Name    : tb.cew
//
// Purpose      : design verification
//
// Author       : Peter Walsh, Vancouver Island University
//
// System       : icarus (Linux)
//
//------------------------------------------------------------------
// Revision List
// Version      Author  Date    Changes
// 1.0          PW      Nov 2016  New version
//================================================================--














`include "controlSignal.v" 


module test_bench();

   integer cew_Test_Count=0;
          integer cew_Error_Count=0;

   reg t_reset, t_clk;
   wire  t_fault, t_halt, t_break;
   wire  [0:`MAX_CONTROL_LINES-1] t_control;
   reg [3:0] t_opcode;
   reg [15:0] t_psw;


   control_unit cut (t_control, t_clk, t_opcode, t_psw, t_reset, t_halt, t_fault, t_break);

   task clockTick; 
      begin // nasty syntax
         t_clk<=0; #3; 
         t_clk<=1; #6;
         t_clk<=0; #3;
      end
   endtask

   initial begin
      $dumpfile("test_bench.vcd");
      $dumpvars(0,test_bench);

      t_reset<=0;#1;t_reset<=1;#1; t_reset<=0;#1;
      t_opcode <= 4'b0001;
      clockTick();
      clockTick();
      clockTick();
      clockTick();
      cew_Test_Count=cew_Test_Count+1;
          
          if ((t_halt) !== (1'b1)) begin
             cew_Error_Count=cew_Error_Count+1;
             $display("\nTest Case ERROR (Ncase) in script at line number 52");
             $display("Actual Value is ", t_halt );
             $display("Expected Value is ", 1'b1 );
          end


      $display("\n**********Summary**********\n");
          $display("Total number of test cases = %d \n", cew_Test_Count);
          $display("Total number of test cases in error = %d \n", cew_Error_Count);

      #1 $finish();
   end

endmodule

Verilog/v1-r1-MMA/Control_Unit/test_bench.vcd
$date
	Tue Dec 18 00:31:44 2018
$end
$version
	Icarus Verilog
$end
$timescale
	1s
$end
$scope module test_bench $end
$var wire 1 ! t_halt $end
$var wire 1 " t_fault $end
$var wire 14 # t_control [0:13] $end
$var wire 1 $ t_break $end
$var reg 1 % t_clk $end
$var reg 4 & t_opcode [3:0] $end
$var reg 16 ' t_psw [15:0] $end
$var reg 1 ( t_reset $end
$var integer 32 ) cew_Error_Count [31:0] $end
$var integer 32 * cew_Test_Count [31:0] $end
$scope module cut $end
$var wire 1 % clk $end
$var wire 4 + opcode [3:0] $end
$var wire 16 , psw [15:0] $end
$var wire 1 ( reset $end
$var reg 1 $ break $end
$var reg 14 - control [0:13] $end
$var reg 1 " fault $end
$var reg 1 ! halt $end
$var reg 5 . nextState [4:0] $end
$var reg 5 / state [4:0] $end
$scope task clearControl $end
$var integer 32 0 i [31:0] $end
$upscope $end
$upscope $end
$scope task clockTick $end
$upscope $end
$upscope $end
$enddefinitions $end
#0
$dumpvars
bx 0
bx /
bx .
bx -
bx ,
bx +
b0 *
b0 )
0(
bx '
bx &
x%
x$
bx #
x"
x!
$end
#1
b0 #
b0 -
b1110 0
0$
0"
0!
b0 /
1(
#2
b1 .
b1000000000000 #
b1000000000000 -
0(
#3
b0 #
b0 -
b1110 0
0%
b1 &
b1 +
#4
b1000000000000 #
b1000000000000 -
#6
b0 #
b0 -
b1110 0
b1 /
1%
#7
b10 .
b100 #
b100 -
#12
0%
#18
b0 #
b0 -
b1110 0
b10 /
1%
#19
b11 .
b110000000000 #
b110000000000 -
#24
0%
#30
b0 #
b0 -
b1110 0
b11 /
1%
#31
1!
1$
#36
0%
#42
1%
#48
0%
#51
b1 *
