Verilog/v1-r1-MMA/Include/controlSignal.v
//================================================================--
// Design Unit	: control names (include)
//
// File Name	: controlSignal.v
//
// Purpose	: include file with control signal names
//
// Author	: Peter Walsh, Vancouver Island University
//
// Environmant	: Icarus
//-------------------------------------------------------------------
// Revision List	
// Version	Author		Date	   Changes
// 1.0		PW		Nov 2016   New version
// 2.0          Sami Al-Qusus   Nov 2018   Modified for MMA 
//================================================================--

//Control signals are all asserted active-high.
//The define macros below are used to enhance readability
//by replacing references like control[0] with control[HALT].
//
//Registers
//---------
//Program counter (PC) 12 bits
//ALU registers (R0, R1, R2, R3) 8 bits each
//Instruction Register (IR) 16 bits
//
//Busses/Signals
//--------------
//Internal address bus (int_abus) 12 bits
//Internal read data bus (int_rbus) 16 bits
//Internal write data bus (int_wbus) 16 bits
//ALU output (alu_out) 8 bits

`define MAX_CONTROL_LINES 14
//control[0:MAX_CONTROL_LINES-1]

`define WE 0 
// (WE) ? MEM mwmoey write cycle : memory read cycle
`define INIT_PC 1
// PC <= 0 
`define INC_PC 2
// PC <=  PC + 1
`define IR_RBUS 3
// IR <= int_rbus 
`define R0_RBUS 4
// R0 <= int_rbus 
`define ACC_RBUS 5
// R1 <= int_rbus 
`define WBUS_ACC 6
// int_wbus <= ACC
`define ACC_ALU 7
// int_wbus <= alu
`define ADD_OP 8
// R0 + R1
`define SUB_OP 9 
// R1 - R0
`define ABUS_MR 10
// int_abus <= MR
`define ABUS_PC 11
// int_abus <= PC
`define PC_R0 12
// PC <= R0
`define MR_R0 13
// MR <=  R0

Verilog/v1-r1-MMA/Data_Path/behaviour.v
//================================================================--
// Design Unit	: data_path (behaviour)
//
// File Name	: behaviour.v
//
// Purpose	: implement MMA data path 
//
// Author	: Peter Walsh, Vancouver Island University
//
// Environmant	: Icarus
//-------------------------------------------------------------------
// Revision List	
// Version	Author		Date	  Changes
// 1.0		PW		Nov 2016   New version
// 2.0          Sami Al-Qusus   Nov 2018   MMA 
//================================================================--

`include "controlSignal.v"

module data_path (control, IR, int_rbus, int_wbus, int_abus, Z, clk); 

   input wire clk;
   input wire [15:0] int_rbus;
   output wire [15:0] int_abus;
   output wire [15:0] int_wbus;
   output wire Z;
   output reg [3:0] IR;
   input wire [0:`MAX_CONTROL_LINES-1] control;


   reg [15:0] R0, ACC, RN;
   reg [15:0] PC, MR;
   reg [15:0] wbus, rbus, alu;
   reg [15:0] abus;

   always @(posedge clk) begin

      if (control[`INIT_PC] == 1'b1)
         PC <= 16'h0000;

      if (control[`INC_PC] == 1'b1)
          PC <= PC + 1;

      if (control[`IR_RBUS] == 1'b1)
          IR <= int_rbus[15:12];

      if (control[`R0_RBUS] == 1'b1)
          R0 <= int_rbus[11:0];

	     if (control[`ACC_RBUS] == 1'b1)
    	          ACC <= int_rbus;

     	
	  if (control[`ACC_ALU] == 1'b1)
        	  ACC <= alu;
    
     
     if (control[`PC_R0] == 1'b1)
         PC <= R0;

      if (control[`MR_R0] == 1'b1)
         MR <= R0;

   end
  
  // always@(control[`ACC_RBUS], control[`ACC_ALU], RBUS, ALU) begin
//	   if (control[`ACC_RBUS] == 1'b1)
//		   ACC <= int_rbus;
//	   if (control[`ACC_ALU] == 1'b1)
//		   ACC <= alu;
 //  end

   always@(control[`ABUS_PC], control[`ABUS_MR], PC, MR) begin

      if (control[`ABUS_PC] == 1'b1)
          abus <= PC;

      if (control[`ABUS_MR] == 1'b1)
          abus <= MR;
   end 

   always@(control[`ADD_OP], control[`SUB_OP], R0, ACC) begin

      if (control[`ADD_OP] == 1'b1)
         alu <= R0 + ACC;

      if (control[`SUB_OP] == 1'b1) begin
         RN = ~R0 + 1'b1; // blocking assignment
         alu <= ACC + RN;
      end

   end

   always@(control[`WBUS_ACC], ACC) begin

      if (control[`WBUS_ACC] == 1'b1)
         wbus <= ACC;
   end

   assign Z = (alu == 16'b0000000000000000) ? 1'b1 : 1'b0;
   assign int_abus = abus;
   assign int_wbus = wbus;

endmodule

Verilog/v1-r1-MMA/Data_Path/tb.v
//================================================================--
// Design Unit  : cew testbench for data_path
//
// File Name    : tb.cew
//
// Purpose      : design verification
//
// Author       : Peter Walsh, Vancouver Island University
//
// System       : icarus (Linux)
//
//------------------------------------------------------------------
// Revision List
// Version      Author  Date    Changes
// 1.0          PW      Nov 2016  New version
//================================================================--














`include "controlSignal.v" 


module test_bench();

   integer cew_Test_Count=0;
          integer cew_Error_Count=0;


   reg t_clk;
   reg [15:0] t_int_rbus;
   wire [11:0] t_int_abus;
   wire [15:0] t_int_wbus;
   wire t_Z;
   wire [3:0] t_IR;
   reg [0:`MAX_CONTROL_LINES-1] t_control;

   data_path cut (t_control, t_IR, t_int_rbus, t_int_wbus, t_int_abus, t_Z, t_clk);

   task clearControl;

      integer i;

      begin
         for (i=0; i<`MAX_CONTROL_LINES; i=i+1)
            t_control[i] <= 1'b0;
         #1;
      end

   endtask

   task clockTick; 

      begin // nasty syntax
         t_clk<=0; #3; 
         t_clk<=1; #6;
         t_clk<=0; #3;
      end

   endtask

   initial begin
      $dumpfile("test_bench.vcd");
      $dumpvars(0,test_bench);

      // move data from PC to abus

      clearControl();
      t_control[`INIT_PC] <= 1'b1;
      clockTick();
      t_control[`INC_PC] <= 1'b1;
      clockTick();
      t_control[`ABUS_PC] <= 1'b1;#1;
      cew_Test_Count=cew_Test_Count+1;
          
          if ((t_int_abus) !== (1)) begin
             cew_Error_Count=cew_Error_Count+1;
             $display("\nTest Case ERROR (Ncase) in script at line number 70");
             $display("Actual Value is ", t_int_abus );
             $display("Expected Value is ", 1 );
          end


    
      // move data from rbus to IR

      clearControl();
      t_int_rbus <= 4'h0;
      t_control[`IR_RBUS] <= 1'b1; 
      clockTick();
      cew_Test_Count=cew_Test_Count+1;
          
          if ((t_IR) !== (4'h0)) begin
             cew_Error_Count=cew_Error_Count+1;
             $display("\nTest Case ERROR (Ncase) in script at line number 79");
             $display("Actual Value is ", t_IR );
             $display("Expected Value is ", 4'h0 );
          end


      // move data from rbus to alu(add) to wbus and flags

      clearControl();
      t_int_rbus <= 16'h00;
      t_control[`R0_RBUS] <= 1'b1;
      t_control[`ACC_RBUS] <= 1'b1;
      clockTick();
      t_control[`ADD_OP] <= 1'b1;
      t_control[`ACC_ALU] <= 1'b1;
      clockTick();
      cew_Test_Count=cew_Test_Count+1;
          
          if ((t_Z) !== (1'b1)) begin
             cew_Error_Count=cew_Error_Count+1;
             $display("\nTest Case ERROR (Ncase) in script at line number 91");
             $display("Actual Value is ", t_Z );
             $display("Expected Value is ", 1'b1 );
          end

      t_control[`WBUS_ACC] <= 1'b1;#1;
      cew_Test_Count=cew_Test_Count+1;
          
          if ((t_int_wbus) !== (16'h00)) begin
             cew_Error_Count=cew_Error_Count+1;
             $display("\nTest Case ERROR (Ncase) in script at line number 93");
             $display("Actual Value is ", t_int_wbus );
             $display("Expected Value is ", 16'h00 );
          end


      // move data from rbus to PC to abus 
    
      clearControl();
      t_int_rbus <= 16'h01;
      t_control[`R0_RBUS] <= 1'b1;
      clockTick();
      t_control[`PC_R0] <= 1'b1;
      clockTick();
      t_control[`ABUS_PC] <= 1'b1;#1;
      cew_Test_Count=cew_Test_Count+1;
          
          if ((t_int_abus) !== (16'h01)) begin
             cew_Error_Count=cew_Error_Count+1;
             $display("\nTest Case ERROR (Ncase) in script at line number 104");
             $display("Actual Value is ", t_int_abus );
             $display("Expected Value is ", 16'h01 );
          end


      $display("\n**********Summary**********\n");
          $display("Total number of test cases = %d \n", cew_Test_Count);
          $display("Total number of test cases in error = %d \n", cew_Error_Count);

      #1 $finish();
   end

endmodule

Verilog/v1-r1-MMA/Data_Path/test_bench.vcd
$date
	Mon Dec 17 22:20:11 2018
$end
$version
	Icarus Verilog
$end
$timescale
	1s
$end
$scope module test_bench $end
$var wire 16 ! t_int_wbus [15:0] $end
$var wire 12 " t_int_abus [11:0] $end
$var wire 1 # t_Z $end
$var wire 4 $ t_IR [3:0] $end
$var reg 1 % t_clk $end
$var reg 14 & t_control [0:13] $end
$var reg 16 ' t_int_rbus [15:0] $end
$var integer 32 ( cew_Error_Count [31:0] $end
$var integer 32 ) cew_Test_Count [31:0] $end
$scope module cut $end
$var wire 1 % clk $end
$var wire 14 * control [0:13] $end
$var wire 16 + int_abus [15:0] $end
$var wire 16 , int_rbus [15:0] $end
$var wire 16 - int_wbus [15:0] $end
$var wire 1 # Z $end
$var reg 16 . ACC [15:0] $end
$var reg 4 / IR [3:0] $end
$var reg 16 0 MR [15:0] $end
$var reg 16 1 PC [15:0] $end
$var reg 16 2 R0 [15:0] $end
$var reg 16 3 RN [15:0] $end
$var reg 16 4 abus [15:0] $end
$var reg 16 5 alu [15:0] $end
$var reg 16 6 wbus [15:0] $end
$upscope $end
$scope task clearControl $end
$var integer 32 7 i [31:0] $end
$upscope $end
$scope task clockTick $end
$upscope $end
$upscope $end
$enddefinitions $end
#0
$dumpvars
b1110 7
bx 6
bx 5
bx 4
bx 3
bx 2
bx 1
bx 0
bx /
bx .
bx -
bx ,
bx +
b0 *
b0 )
b0 (
bx '
b0 &
x%
bx $
x#
bx "
bx !
$end
#1
0%
b1000000000000 &
b1000000000000 *
#4
b0 1
1%
#10
0%
#13
b1100000000000 &
b1100000000000 *
#16
b1 1
1%
#22
0%
#25
b1 "
b1 +
b1 4
b1100000000100 &
b1100000000100 *
#26
b0 &
b0 *
b1110 7
b1 )
#27
b10000000000 &
b10000000000 *
b0 '
b0 ,
#30
b0 $
b0 /
1%
#36
0%
#39
b0 &
b0 *
b1110 7
b10 )
#40
b1100000000 &
b1100000000 *
#43
b0 .
b0 2
1%
#49
0%
#52
1#
b0 5
b1101100000 &
b1101100000 *
#55
1%
#61
0%
#64
b0 !
b0 -
b0 6
b1111100000 &
b1111100000 *
b11 )
#65
b0 &
b0 *
b1110 7
b100 )
#66
b1000000000 &
b1000000000 *
b1 '
b1 ,
#69
b1 2
1%
#75
0%
#78
b1000000010 &
b1000000010 *
#81
1%
#87
0%
#90
b1000000110 &
b1000000110 *
#91
b101 )
