Lab9/behaviour.v
//================================================================--
// Design Unit	: lab9 (behaviour)
//
// File Name	: behaviour.v
//
// Purpose	: implement traffic light controller
//
// Author	: Peter Walsh, Vancouver Island University
//
// Environmant	: Icarus
//-------------------------------------------------------------------
// Revision List	
// Version	Author	Date	Changes
// 1.0		PW	Sept 10 New version
// 1.1		PW	June 20 2013 review
//================================================================--

module lab9 (state,  clk, sto, lto, car, reset, Hlights, Flights); 

   output reg [2:0] Hlights, Flights;
   // light order is red green yellow 
   // eg HG -> Hlights==010 -> green highway on others off.
   input wire clk, reset, sto, lto, car;
   output reg [1:0] state;
   reg [1:0] nextState;
   reg [2:0] inp;

   parameter HG = 2'b00, HY = 2'b01, FG = 2'b11, FY = 2'b10;

   // state assignment

   always @(posedge clk, negedge reset) begin
      if (reset == 0)
         state<=HG;
      else
         state<=nextState;
   end

   // next state functions

   always @(state, sto, lto, car) begin
      inp={sto,lto,car};
      case (state)
         HG: begin
            Hlights= 3'b 010;
            Flights= 3'b 100;
            case  (inp)
               3'b000: nextState<=HG;
               3'b001: nextState<=HG;
               3'b010: nextState<=HG;
               3'b011: nextState<=HY;
               3'b100: nextState<=HG;
               3'b101: nextState<=HG;
               3'b110: nextState<=HG;
               3'b111: nextState<=HY;
            endcase
         end
         HY: begin
            Hlights= 3'b 001;
            Flights= 3'b 100;
            case  (inp)
               3'b000: nextState<=HY;
               3'b001: nextState<=HY;
               3'b010: nextState<=HY;
               3'b011: nextState<=HY;
               3'b100: nextState<=FG;
               3'b101: nextState<=FG;
               3'b110: nextState<=FG;
               3'b111: nextState<=FG;
            endcase
         end
         FG: begin
            Hlights= 3'b 100;
            Flights= 3'b 010;
            case  (inp)
               3'b000: nextState<=FG;
               3'b001: nextState<=FG;
               3'b010: nextState<=FY;
               3'b011: nextState<=FY;
               3'b100: nextState<=FY;
               3'b101: nextState<=FG;
               3'b110: nextState<=FY;
               3'b111: nextState<=FY;
            endcase
         end
         FY: begin
            Hlights= 3'b 100;
            Flights= 3'b 001;
            case  (inp)
               3'b000: nextState<=FY;
               3'b001: nextState<=FY;
               3'b010: nextState<=FY;
               3'b011: nextState<=FY;
               3'b100: nextState<=HG;
               3'b101: nextState<=HG;
               3'b110: nextState<=HG;
               3'b111: nextState<=HG;
            endcase
         end

     endcase 
   end

endmodule

Lab9/tb.v
//================================================================--
// Design Unit  : cew testbench lab9
//
// File Name    : tb.cew
//
// Purpose      : design verification
//
// Author       : Peter Walsh, Vancouver Island University
//
// System       : icarus (Linux)
//
//------------------------------------------------------------------
// Revision List
// Version      Author  Date    Changes
// 1.0          PW      Sep 10  New version
//================================================================--












module test_bench();

   integer cew_Test_Count=0;
          integer cew_Error_Count=0;

   reg t_reset, t_clk, t_sto, t_lto, t_car;
   wire [2:0] t_Hlights, t_Flights;
   wire [1:0] t_state;

   // state  encoding
   localparam t_HG = 2'b00, t_HY = 2'b01, t_FG = 2'b11, t_FY = 2'b10;

   lab9 cut (t_state,  t_clk, t_sto, t_lto, t_car, t_reset, t_Hlights, t_Flights);

   task clockTick; 
      begin // nasty syntax
         t_clk=0; #3; 
         t_clk=1; #6;
         t_clk=0; #3;
      end
   endtask

   task setState;

      input [1:0]  x;

      begin

         t_reset<=1;#1;t_reset<=0;#1; t_reset<=1;#1;
         case (x)
            t_HG: begin
            end
            t_HY: begin
              t_sto=0;t_lto=1;t_car=1;clockTick(); 
            end
            t_FG: begin
              t_sto=0;t_lto=1;t_car=1;clockTick(); 
              t_sto=1;t_lto=0;t_car=0;clockTick(); 
            end
            t_FY: begin
              t_sto=0;t_lto=1;t_car=1;clockTick(); 
              t_sto=1;t_lto=0;t_car=0;clockTick(); 
              t_sto=0;t_lto=1;t_car=0;clockTick(); 
            end
         endcase
      end
 
   endtask

   initial begin
      $dumpfile("test_bench.vcd");
      $dumpvars(0,test_bench);

      // State t_HG
      cew_Test_Count=cew_Test_Count+1;
          setState(t_HG);
          if ((t_state) !== (t_HG)) begin
             cew_Error_Count=cew_Error_Count+1;
             $display("\nTest Case ERROR (Ncase) in script at line number 73");
             $display("Actual Value is ", t_state );
             $display("Expected Value is ", t_HG );
          end

      cew_Test_Count=cew_Test_Count+1;
          
          if ((t_Hlights) !== (3'b 010)) begin
             cew_Error_Count=cew_Error_Count+1;
             $display("\nTest Case ERROR (Ncase) in script at line number 74");
             $display("Actual Value is ", t_Hlights );
             $display("Expected Value is ", 3'b 010 );
          end

      cew_Test_Count=cew_Test_Count+1;
          
          if ((t_Flights) !== (3'b 100)) begin
             cew_Error_Count=cew_Error_Count+1;
             $display("\nTest Case ERROR (Ncase) in script at line number 75");
             $display("Actual Value is ", t_Flights );
             $display("Expected Value is ", 3'b 100 );
          end


      // State t_HY
      cew_Test_Count=cew_Test_Count+1;
          setState(t_HY);
          if ((t_state) !== (t_HY)) begin
             cew_Error_Count=cew_Error_Count+1;
             $display("\nTest Case ERROR (Ncase) in script at line number 78");
             $display("Actual Value is ", t_state );
             $display("Expected Value is ", t_HY );
          end

      cew_Test_Count=cew_Test_Count+1;
          
          if ((t_Hlights) !== (3'b 001)) begin
             cew_Error_Count=cew_Error_Count+1;
             $display("\nTest Case ERROR (Ncase) in script at line number 79");
             $display("Actual Value is ", t_Hlights );
             $display("Expected Value is ", 3'b 001 );
          end

      cew_Test_Count=cew_Test_Count+1;
          
          if ((t_Flights) !== (3'b 100)) begin
             cew_Error_Count=cew_Error_Count+1;
             $display("\nTest Case ERROR (Ncase) in script at line number 80");
             $display("Actual Value is ", t_Flights );
             $display("Expected Value is ", 3'b 100 );
          end


      // State t_FG
      cew_Test_Count=cew_Test_Count+1;
          setState(t_FG);
          if ((t_state) !== (t_FG)) begin
             cew_Error_Count=cew_Error_Count+1;
             $display("\nTest Case ERROR (Ncase) in script at line number 83");
             $display("Actual Value is ", t_state );
             $display("Expected Value is ", t_FG );
          end

      cew_Test_Count=cew_Test_Count+1;
          
          if ((t_Hlights) !== (3'b 100)) begin
             cew_Error_Count=cew_Error_Count+1;
             $display("\nTest Case ERROR (Ncase) in script at line number 84");
             $display("Actual Value is ", t_Hlights );
             $display("Expected Value is ", 3'b 100 );
          end

      cew_Test_Count=cew_Test_Count+1;
          
          if ((t_Flights) !== (3'b 010)) begin
             cew_Error_Count=cew_Error_Count+1;
             $display("\nTest Case ERROR (Ncase) in script at line number 85");
             $display("Actual Value is ", t_Flights );
             $display("Expected Value is ", 3'b 010 );
          end


      // State t_FY_
      cew_Test_Count=cew_Test_Count+1;
          setState(t_FY);
          if ((t_state) !== (t_FY)) begin
             cew_Error_Count=cew_Error_Count+1;
             $display("\nTest Case ERROR (Ncase) in script at line number 88");
             $display("Actual Value is ", t_state );
             $display("Expected Value is ", t_FY );
          end

      cew_Test_Count=cew_Test_Count+1;
          
          if ((t_Hlights) !== (3'b 100)) begin
             cew_Error_Count=cew_Error_Count+1;
             $display("\nTest Case ERROR (Ncase) in script at line number 89");
             $display("Actual Value is ", t_Hlights );
             $display("Expected Value is ", 3'b 100 );
          end

      cew_Test_Count=cew_Test_Count+1;
          
          if ((t_Flights) !== (3'b 001)) begin
             cew_Error_Count=cew_Error_Count+1;
             $display("\nTest Case ERROR (Ncase) in script at line number 90");
             $display("Actual Value is ", t_Flights );
             $display("Expected Value is ", 3'b 001 );
          end


      $display("\n**********Summary**********\n");
          $display("Total number of test cases = %d \n", cew_Test_Count);
          $display("Total number of test cases in error = %d \n", cew_Error_Count);

      #1 $finish();
   end

endmodule

Lab9/behaviour.vcd
$date
	Thu Nov 22 19:04:43 2018
$end
$version
	Icarus Verilog
$end
$timescale
	1s
$end
$scope module test_bench $end
$var wire 2 ! t_state [1:0] $end
$var wire 3 " t_Hlights [2:0] $end
$var wire 3 # t_Flights [2:0] $end
$var reg 1 $ t_car $end
$var reg 1 % t_clk $end
$var reg 1 & t_lto $end
$var reg 1 ' t_reset $end
$var reg 1 ( t_sto $end
$var integer 32 ) cew_Error_Count [31:0] $end
$var integer 32 * cew_Test_Count [31:0] $end
$scope module cut $end
$var wire 1 $ car $end
$var wire 1 % clk $end
$var wire 1 & lto $end
$var wire 1 ' reset $end
$var wire 1 ( sto $end
$var reg 3 + Flights [2:0] $end
$var reg 3 , Hlights [2:0] $end
$var reg 3 - inp [2:0] $end
$var reg 2 . nextState [1:0] $end
$var reg 2 / state [1:0] $end
$upscope $end
$scope task clockTick $end
$upscope $end
$scope task setState $end
$var reg 2 0 x [1:0] $end
$upscope $end
$upscope $end
$enddefinitions $end
#0
$dumpvars
b0 0
bx /
bx .
bx -
bx ,
bx +
b1 *
b0 )
x(
1'
x&
x%
x$
bx #
bx "
bx !
$end
#1
b100 #
b100 +
b10 "
b10 ,
b0 !
b0 /
0'
#2
1'
#3
b1 0
b100 *
#4
0'
#5
1'
#6
b1 .
b11 -
0%
1$
1&
0(
#9
b1 "
b1 ,
b1 !
b1 /
1%
#15
0%
#18
b11 0
b111 *
#19
b10 "
b10 ,
b0 !
b0 /
0'
#20
1'
#24
b1 "
b1 ,
b1 !
b1 /
1%
#30
0%
#33
b11 .
b100 -
0$
0&
1(
#36
b10 .
b10 #
b10 +
b100 "
b100 ,
b11 !
b11 /
1%
#42
0%
#45
b10 0
b1010 *
#46
b0 .
b100 #
b100 +
b10 "
b10 ,
b0 !
b0 /
0'
#47
1'
#48
b1 .
b11 -
1$
1&
0(
#51
b1 "
b1 ,
b1 !
b1 /
1%
#57
0%
#60
b11 .
b100 -
0$
0&
1(
#63
b10 .
b10 #
b10 +
b100 "
b100 ,
b11 !
b11 /
1%
#69
0%
#72
b10 -
1&
0(
#75
b1 #
b1 +
b10 !
b10 /
1%
#81
0%
#84
b1100 *
