Lab1/behaviour.v
//================================================================--
// Design Unit	: lab1 (behaviour)
//
// File Name	: behaviour.v
//
// Purpose	: implement logic diagram from Exp 1
//
// Note		:
//
// Limitations	:
//
// Errors	: none known
//
// Library 	: none
//
// Dependences	: none
//
// Author	: Peter Walsh, Vancouver Island University
//
// Environmant	: Icarus
//-------------------------------------------------------------------
// Revision List	
// Version	Author	Date	Changes
// 1.0		PW	Sept 10 New version
// 1.1		PW	June 20 2013 review
//================================================================--

module lab1 (D, A, B, C); 

   output reg D;
   input wire A, B, C;

   always @(A, B, C) begin
      D <= ((A | B) & (A | C)) ~& (B | C);
   end

endmodule

Lab1/tb.v
//================================================================--
// Design Unit  : cew testbench for lab1
//
// File Name    : tb.cew
//
// Purpose      : design verification
//
// Note         :
//
// Limitations  :
//
// Errors       : none known
//
// Library      : lab1 
//
// Dependences  : none
//
// Author       : Peter Walsh, Vancouver Island University
//
// System       : icarus (Linux)
//
//------------------------------------------------------------------
// Revision List
// Version      Author  Date    Changes
// 1.0          PW      Sep 10  New version
//================================================================--















module test_bench();

   integer cew_Test_Count=0;
          integer cew_Error_Count=0;

   wire t_D;
   reg t_A, t_B, t_C;

   lab1 cut(t_D, t_A, t_B, t_C);

   initial begin
      $dumpfile("test_bench.vcd");
      $dumpvars(0,test_bench);

      cew_Test_Count=cew_Test_Count+1;
          t_A=0;t_B=0;t_C=0;#1;
          if ((t_D) !== (1)) begin
             cew_Error_Count=cew_Error_Count+1;
             $display("\nTest Case ERROR (Ncase) in script at line number 43");
             $display("Actual Value is ", t_D );
             $display("Expected Value is ", 1 );
          end

      cew_Test_Count=cew_Test_Count+1;
          t_A=0;t_B=0;t_C=1;#1;
          if ((t_D) !== (1)) begin
             cew_Error_Count=cew_Error_Count+1;
             $display("\nTest Case ERROR (Ncase) in script at line number 44");
             $display("Actual Value is ", t_D );
             $display("Expected Value is ", 1 );
          end

      cew_Test_Count=cew_Test_Count+1;
          t_A=0;t_B=1;t_C=0;#1;
          if ((t_D) !== (1)) begin
             cew_Error_Count=cew_Error_Count+1;
             $display("\nTest Case ERROR (Ncase) in script at line number 45");
             $display("Actual Value is ", t_D );
             $display("Expected Value is ", 1 );
          end

      cew_Test_Count=cew_Test_Count+1;
          t_A=0;t_B=1;t_C=1;#1;
          if ((t_D) !== (0)) begin
             cew_Error_Count=cew_Error_Count+1;
             $display("\nTest Case ERROR (Ncase) in script at line number 46");
             $display("Actual Value is ", t_D );
             $display("Expected Value is ", 0 );
          end

      cew_Test_Count=cew_Test_Count+1;
          t_A=1;t_B=0;t_C=0;#1;
          if ((t_D) !== (1)) begin
             cew_Error_Count=cew_Error_Count+1;
             $display("\nTest Case ERROR (Ncase) in script at line number 47");
             $display("Actual Value is ", t_D );
             $display("Expected Value is ", 1 );
          end

      cew_Test_Count=cew_Test_Count+1;
          t_A=1;t_B=0;t_C=1;#1;
          if ((t_D) !== (0)) begin
             cew_Error_Count=cew_Error_Count+1;
             $display("\nTest Case ERROR (Ncase) in script at line number 48");
             $display("Actual Value is ", t_D );
             $display("Expected Value is ", 0 );
          end

      cew_Test_Count=cew_Test_Count+1;
          t_A=1;t_B=1;t_C=0;#1;
          if ((t_D) !== (0)) begin
             cew_Error_Count=cew_Error_Count+1;
             $display("\nTest Case ERROR (Ncase) in script at line number 49");
             $display("Actual Value is ", t_D );
             $display("Expected Value is ", 0 );
          end

      cew_Test_Count=cew_Test_Count+1;
          t_A=1;t_B=1;t_C=1;#1;
          if ((t_D) !== (0)) begin
             cew_Error_Count=cew_Error_Count+1;
             $display("\nTest Case ERROR (Ncase) in script at line number 50");
             $display("Actual Value is ", t_D );
             $display("Expected Value is ", 0 );
          end

      $display("\n**********Summary**********\n");
          $display("Total number of test cases = %d \n", cew_Test_Count);
          $display("Total number of test cases in error = %d \n", cew_Error_Count);

      #1 $finish();
   end

endmodule

Lab1/behaviour.vcd
$date
	Thu Sep 13 15:43:44 2018
$end
$version
	Icarus Verilog
$end
$timescale
	1s
$end
$scope module test_bench $end
$var wire 1 ! t_D $end
$var reg 1 " t_A $end
$var reg 1 # t_B $end
$var reg 1 $ t_C $end
$var integer 32 % cew_Error_Count [31:0] $end
$var integer 32 & cew_Test_Count [31:0] $end
$scope module cut $end
$var wire 1 " A $end
$var wire 1 # B $end
$var wire 1 $ C $end
$var reg 1 ! D $end
$upscope $end
$upscope $end
$enddefinitions $end
#0
$dumpvars
b1 &
b0 %
0$
0#
0"
1!
$end
#1
1$
b10 &
#2
0$
1#
b11 &
#3
0!
1$
b100 &
#4
1!
0$
0#
1"
b101 &
#5
0!
1$
b110 &
#6
0$
1#
b111 &
#7
1$
b1000 &
