Lab2/behaviour.v
//================================================================--
// Design Unit	: lab2 (behaviour)
//
// File Name	: behaviour.v
//
// Purpose	: implement logic diagram from Exp 2
//
// Note		:
//
// Limitations	:
//
// Errors	: none known
//
// Library 	: none
//
// Dependences	: none
//
// Author	: Peter Walsh, Vancouver Island University
//
// Environmant	: Icarus
//-------------------------------------------------------------------
// Revision List	
// Version	Author	Date	Changes
// 1.0		PW	Sept 10 New version
// 1.1		PW	June 20 2013 review
//================================================================--

module lab2 (E, A, B, C, D); 

   output reg E;
   input wire A, B, C, D;

   always @(A, B, C, D) begin
      // structural logic description (not minimized)
      E <= ((~A & ~C) & (B ^ D)) | (~B & C);
   end

endmodule

Lab2/tb.v
//================================================================--
// Design Unit  : cew testbench for lab2
//
// File Name    : tb.cew
//
// Purpose      : design verification
//
// Note         :
//
// Limitations  :
//
// Errors       : none known
//
// Library      : lab2
//
// Dependences  : none
//
// Author       : Peter Walsh, Vancouver Island University
//		  (Edited By: Sami Al-Qusus)
// System       : icarus (Linux)
//
//------------------------------------------------------------------
// Revision List
// Version      Author  Date    Changes
// 1.0          PW      Sep 10  New version
// 2.0          SA      Oct 4   Added requested code for Lab2
//================================================================--















module test_bench();

   integer cew_Test_Count=0;
          integer cew_Error_Count=0;

   wire t_E;
   reg t_A, t_B, t_C, t_D;
   integer i;

   // Gold function
    function gold;
       input w,x,y,z;
 
       gold=((~w&x&~y&~z)|(~w&~x&z)|(~x&y));

    endfunction


   lab2 cut(t_E, t_A, t_B, t_C, t_D);

   initial begin
      $dumpfile("test_bench.vcd");
      $dumpvars(0,test_bench);
      for (i=0; i<16; i=i+1)
	begin
        cew_Test_Count=cew_Test_Count+1;
          t_A=i[3];t_B=i[2];t_C=i[1];t_D=i[0];#1;
          if ((t_E) !== (gold(t_A,t_B,t_C,t_D))) begin
             cew_Error_Count=cew_Error_Count+1;
             $display("\nTest Case ERROR (Ncase) in script at line number 55");
             $display("Actual Value is ", t_E );
             $display("Expected Value is ", gold(t_A,t_B,t_C,t_D) );
          end

      end
      $display("\n**********Summary**********\n");
          $display("Total number of test cases = %d \n", cew_Test_Count);
          $display("Total number of test cases in error = %d \n", cew_Error_Count);

      #1 $finish();
   end

endmodule

Lab2/behaviour.vcd
$date
	Thu Oct  4 00:01:04 2018
$end
$version
	Icarus Verilog
$end
$timescale
	1s
$end
$scope module test_bench $end
$var wire 1 ! t_E $end
$var reg 1 " t_A $end
$var reg 1 # t_B $end
$var reg 1 $ t_C $end
$var reg 1 % t_D $end
$var integer 32 & cew_Error_Count [31:0] $end
$var integer 32 ' cew_Test_Count [31:0] $end
$var integer 32 ( i [31:0] $end
$scope function gold $end
$var reg 1 ) gold $end
$var reg 1 * w $end
$var reg 1 + x $end
$var reg 1 , y $end
$var reg 1 - z $end
$upscope $end
$scope module cut $end
$var wire 1 " A $end
$var wire 1 # B $end
$var wire 1 $ C $end
$var wire 1 % D $end
$var reg 1 ! E $end
$upscope $end
$upscope $end
$enddefinitions $end
#0
$dumpvars
x-
x,
x+
x*
x)
b0 (
b1 '
b0 &
0%
0$
0#
0"
0!
$end
#1
1!
1%
b10 '
b1 (
0)
0*
0+
0,
0-
#2
0%
1$
b11 '
b10 (
1)
1-
#3
1%
b100 '
b11 (
1,
0-
#4
0%
0$
1#
b101 '
b100 (
1-
#5
0!
1%
b110 '
b101 (
1+
0,
0-
#6
0%
1$
b111 '
b110 (
0)
1-
#7
1%
b1000 '
b111 (
1,
0-
#8
0%
0$
0#
1"
b1001 '
b1000 (
1-
#9
1%
b1010 '
b1001 (
1*
0+
0,
0-
#10
1!
0%
1$
b1011 '
b1010 (
1-
#11
1%
b1100 '
b1011 (
1)
1,
0-
#12
0!
0%
0$
1#
b1101 '
b1100 (
1-
#13
1%
b1110 '
b1101 (
0)
1+
0,
0-
#14
0%
1$
b1111 '
b1110 (
1-
#15
1%
b10000 '
b1111 (
1,
0-
#16
b10000 (
1-
