Lab3/behaviour.v
//================================================================--
// Design Unit	: lab3 (behaviour)
//
// File Name	: behaviour.v
//
// Purpose	: implement seven segment driver (eq from espresso)
//
//espresso -o eqntott esp.in
//a = (x&!z) | (y) | (!y&z);
//b = (!x) | (!y&z);
//c = (!x) | (!y&z);
//d = (!x&z) | (x&!z) | (!y&z);
//e = (x&!z) | (y) | (!y&z);
//f = (x&!z) | (y) | (!y&z);
//g = (y);
//dp = (!x&!y) | (!w);
//
// Note		:
//
// Limitations	:
//
// Errors	: none known
//
// Library 	: none
//
// Dependences	: none
//
// Author	: Peter Walsh, Vancouver Island University
//
// Environmant	: Icarus
//-------------------------------------------------------------------
// Revision List	
// Version	Author	Date	Changes
// 1.0		PW	Sept 10 New version
// 1.1		PW	June 20 2013 review
//================================================================--

module lab3 (w, x, y, z, a, b, c, d, e, f, g, dp);

   output reg a, b, c, d, e, f, g, dp;
   input wire w, x, y, z;

   always @(w, x, y ,z) begin
      a <= (x & ~z) | (y) | (~y & z);
      b <= (~x) | (~y & z);
      c <= (~x) | (~y & z);
      d <= (~x & z) | (x & ~z) | (~y & z);
      e <= (x & ~z) | (y) | (~y & z);
      f <= (x & ~z) | (y) | (~y & z);
      g <= (y);
      dp <= (~x & ~y) | (~w);

   end

endmodule

Lab3/tb.v
//================================================================--
// Design Unit  : cew testbench for lab3
//
// File Name    : tb.cew
//
// Purpose      : design verification
//
// Note         :
//
// Limitations  :
//
// Errors       : none known
//
// Library      : lab3 
//
// Dependences  : none
//
// Author       : Peter Walsh, Vancouver Island University
//
// System       : icarus (Linux)
//
//------------------------------------------------------------------
// Revision List
// Version      Author  Date    Changes
// 1.0          PW      Sep 10  New version
//================================================================--















module test_bench();

   integer cew_Test_Count=0;
          integer cew_Error_Count=0;

   wire t_a, t_b, t_c, t_d, t_e, t_f, t_g, t_dp;
   reg t_w, t_x, t_y, t_z;
   reg [7:0] t_o;

   integer i;


   lab3 cut(t_w, t_x, t_y, t_z, t_a, t_b, t_c, t_d, t_e, t_f, t_g, t_dp);

   initial begin
      $dumpfile("test_bench.vcd");
      $dumpvars(0,test_bench);


      for (i=0; i<10; i=i+1)
         begin
         cew_Test_Count=cew_Test_Count+1;
          t_w=i[3];t_x=i[2];t_y=i[1];t_z=i[0];#1;
          if ((t_dp) !== (1)) begin
             cew_Error_Count=cew_Error_Count+1;
             $display("\nTest Case ERROR (Ncase) in script at line number 50");
             $display("Actual Value is ", t_dp );
             $display("Expected Value is ", 1 );
          end

         end

      t_w=1;t_x=0;t_y=1;t_z=0;#1;
      t_o={t_a, t_b, t_c, t_d, t_e, t_f, t_g, t_dp};#1;
      cew_Test_Count=cew_Test_Count+1;
          
          if ((t_o) !== (8'b11101110)) begin
             cew_Error_Count=cew_Error_Count+1;
             $display("\nTest Case ERROR (Ncase) in script at line number 55");
             $display("Actual Value is ", t_o );
             $display("Expected Value is ", 8'b11101110 );
          end
 // A

      t_w=1;t_x=0;t_y=1;t_z=1;#1;
      t_o={t_a, t_b, t_c, t_d, t_e, t_f, t_g, t_dp};#1;
      cew_Test_Count=cew_Test_Count+1;
          
          if ((t_o) !== (8'b11111110)) begin
             cew_Error_Count=cew_Error_Count+1;
             $display("\nTest Case ERROR (Ncase) in script at line number 59");
             $display("Actual Value is ", t_o );
             $display("Expected Value is ", 8'b11111110 );
          end
 // B

      t_w=1;t_x=1;t_y=0;t_z=0;#1;
      t_o={t_a, t_b, t_c, t_d, t_e, t_f, t_g, t_dp};#1;
      cew_Test_Count=cew_Test_Count+1;
          
          if ((t_o) !== (8'b10011100)) begin
             cew_Error_Count=cew_Error_Count+1;
             $display("\nTest Case ERROR (Ncase) in script at line number 63");
             $display("Actual Value is ", t_o );
             $display("Expected Value is ", 8'b10011100 );
          end
 // C

      t_w=1;t_x=1;t_y=0;t_z=1;#1;
      t_o={t_a, t_b, t_c, t_d, t_e, t_f, t_g, t_dp};#1;
      cew_Test_Count=cew_Test_Count+1;
          
          if ((t_o) !== (8'b11111100)) begin
             cew_Error_Count=cew_Error_Count+1;
             $display("\nTest Case ERROR (Ncase) in script at line number 67");
             $display("Actual Value is ", t_o );
             $display("Expected Value is ", 8'b11111100 );
          end
 // D

      t_w=1;t_x=1;t_y=1;t_z=0;#1;
      t_o={t_a, t_b, t_c, t_d, t_e, t_f, t_g, t_dp};#1;
      cew_Test_Count=cew_Test_Count+1;
          
          if ((t_o) !== (8'b10011110)) begin
             cew_Error_Count=cew_Error_Count+1;
             $display("\nTest Case ERROR (Ncase) in script at line number 71");
             $display("Actual Value is ", t_o );
             $display("Expected Value is ", 8'b10011110 );
          end
 // E

      t_w=1;t_x=1;t_y=1;t_z=1;#1;
      t_o={t_a, t_b, t_c, t_d, t_e, t_f, t_g, t_dp};#1;
      cew_Test_Count=cew_Test_Count+1;
          
          if ((t_o) !== (8'b10001110)) begin
             cew_Error_Count=cew_Error_Count+1;
             $display("\nTest Case ERROR (Ncase) in script at line number 75");
             $display("Actual Value is ", t_o );
             $display("Expected Value is ", 8'b10001110 );
          end
 // F


      $display("\n**********Summary**********\n");
          $display("Total number of test cases = %d \n", cew_Test_Count);
          $display("Total number of test cases in error = %d \n", cew_Error_Count);

      #1 $finish();
   end

endmodule

Lab3/behaviour.vcd
$date
	Thu Oct 11 19:37:14 2018
$end
$version
	Icarus Verilog
$end
$timescale
	1s
$end
$scope module test_bench $end
$var wire 1 ! t_g $end
$var wire 1 " t_f $end
$var wire 1 # t_e $end
$var wire 1 $ t_dp $end
$var wire 1 % t_d $end
$var wire 1 & t_c $end
$var wire 1 ' t_b $end
$var wire 1 ( t_a $end
$var reg 8 ) t_o [7:0] $end
$var reg 1 * t_w $end
$var reg 1 + t_x $end
$var reg 1 , t_y $end
$var reg 1 - t_z $end
$var integer 32 . cew_Error_Count [31:0] $end
$var integer 32 / cew_Test_Count [31:0] $end
$var integer 32 0 i [31:0] $end
$scope module cut $end
$var wire 1 * w $end
$var wire 1 + x $end
$var wire 1 , y $end
$var wire 1 - z $end
$var reg 1 ( a $end
$var reg 1 ' b $end
$var reg 1 & c $end
$var reg 1 % d $end
$var reg 1 $ dp $end
$var reg 1 # e $end
$var reg 1 " f $end
$var reg 1 ! g $end
$upscope $end
$upscope $end
$enddefinitions $end
#0
$dumpvars
b0 0
b1 /
b0 .
0-
0,
0+
0*
bx )
0(
1'
1&
0%
1$
0#
0"
0!
$end
#1
1"
1#
1%
1(
1-
b10 /
b1 0
#2
1!
0%
0-
1,
b11 /
b10 0
#3
1%
1-
b100 /
b11 0
#4
0!
0&
0'
0-
0,
1+
b101 /
b100 0
#5
1&
1'
1-
b110 /
b101 0
#6
1!
0&
0'
0-
1,
b111 /
b110 0
#7
0%
1-
b1000 /
b111 0
#8
0!
0"
0#
1&
1'
0(
0-
0,
0+
1*
b1001 /
b1000 0
#9
1"
1#
1%
1(
1-
b1010 /
b1001 0
#10
0$
1!
0%
0-
1,
b1010 0
#11
b11101110 )
#12
1%
1-
b1011 /
#13
b11111110 )
#14
0!
0&
0'
0-
0,
1+
b1100 /
#15
b10011100 )
#16
1&
1'
1-
b1101 /
#17
b11111100 )
#18
1!
0&
0'
0-
1,
b1110 /
#19
b10011110 )
#20
0%
1-
b1111 /
#21
b10001110 )
#22
b10000 /
